foldedleastsquares/JAA546A14limb1-4.csv
foldedleastsquares/__init__.py
foldedleastsquares/catalog.py
foldedleastsquares/command_line.py
foldedleastsquares/core.py
foldedleastsquares/fap.csv
foldedleastsquares/gpu.py
foldedleastsquares/grid.py
foldedleastsquares/helpers.py
foldedleastsquares/interpolation.py
foldedleastsquares/ld_claret_tess.csv
foldedleastsquares/main.py
foldedleastsquares/results.py
foldedleastsquares/stats.py
foldedleastsquares/times.py
foldedleastsquares/tls_constants.py
foldedleastsquares/validate.py
foldedleastsquares/version.py
foldedleastsquares/template_generator/__init__.py
foldedleastsquares/template_generator/default_transit_template_generator.py
foldedleastsquares/template_generator/tailed_transit_template_generator.py
foldedleastsquares/template_generator/transit_template_generator.py
foldedleastsquares/tests/EPIC201367065.csv
foldedleastsquares/tests/EPIC201367065_detrended.csv
foldedleastsquares/tests/EPIC206154641.csv
foldedleastsquares/tests/__init__.py
foldedleastsquares/tests/test_FAP.py
foldedleastsquares/tests/test_catalog_data.py
foldedleastsquares/tests/test_cleaned_array.py
foldedleastsquares/tests/test_duration_grid.py
foldedleastsquares/tests/test_multi_planet.py
foldedleastsquares/tests/test_multi_planet_gpu.py
foldedleastsquares/tests/test_period_grid.py
foldedleastsquares/tests/test_resample.py
foldedleastsquares/tests/test_shapes.py
foldedleastsquares/tests/test_stats_gap.py
foldedleastsquares/tests/test_synthetic.py
foldedleastsquares/tests/test_transit_depth_min.py
foldedleastsquares/tests/test_uncertainties.py
foldedleastsquares/tests/test_validation.py
foldedleastsquares/tests/tls_config.cfg
foldedleastsquares/tests/toi237.csv
foldedleastsquares-1.1.11.dist-info/LICENSE
foldedleastsquares-1.1.11.dist-info/METADATA
foldedleastsquares-1.1.11.dist-info/WHEEL
foldedleastsquares-1.1.11.dist-info/top_level.txt
foldedleastsquares-1.1.11.dist-info/RECORD
