Metadata-Version: 2.1
Name: foldedleastsquares
Version: 1.1.11
Summary: An optimized transit-fitting algorithm to search for periodic features in light curves
Home-page: https://github.com/martindevora/tls
Author: Martín Dévora Pajares
Author-email: martin.devora.pajares@gmail.com
License: MIT
Platform: UNKNOWN
Requires-Dist: astropy==7.0.1
Requires-Dist: astroquery==0.4.10
Requires-Dist: numpy==2.1.1
Requires-Dist: numba==0.61.2
Requires-Dist: scipy==1.15.2
Requires-Dist: tqdm
Requires-Dist: batman-package==2.5.3
Requires-Dist: argparse
Requires-Dist: configparser
Requires-Dist: torch==2.7.0
Provides-Extra: cupy
Requires-Dist: 13.4.1; extra == "cupy"
